pycotools/__init__.py
pycotools/_base.py
pycotools/cached_property.py
pycotools/errors.py
pycotools/logging_config.conf
pycotools/misc.py
pycotools/mixin.py
pycotools/model.py
pycotools/models.py
pycotools/retrying.py
pycotools/tasks.py
pycotools/utils.py
pycotools/viz.py
pycotools/zi_model.py
pycotools-1.0.10.dist-info/METADATA
pycotools-1.0.10.dist-info/RECORD
pycotools-1.0.10.dist-info/WHEEL
pycotools-1.0.10.dist-info/top_level.txt
